teranetpracticum/__init__.py
teranetpracticum-0.1.3.data/scripts/__init__.py
teranetpracticum-0.1.3.dist-info/METADATA
teranetpracticum-0.1.3.dist-info/WHEEL
teranetpracticum-0.1.3.dist-info/entry_points.txt
teranetpracticum-0.1.3.dist-info/top_level.txt
teranetpracticum-0.1.3.dist-info/RECORD
