Metadata-Version: 2.1
Name: teranetpracticum
Version: 0.1.3
Summary: teranet practicum package test
Home-page: https://github.com/kaiyuwang-work
Author: kaiyuwang
Author-email: kaiyuwangwork@gmail.com
License: UNKNOWN
Platform: UNKNOWN
